{
    "name": {
        "English": "Metal elemental crystal",
        "Spanish": "Cristal elemental de metal"
    },
    "flavor": {
        "English": "",
        "Spanish": ""
    },

    "rarity": "Legendary",
    "shape": ["X", "X"],
    "type": ["Weapon", "ManaStone"],
    "group": ["Magic"],
    "animation": "Attack",
    "use_limits": { "perTurn": 1, "perCombat": 7 },

    "item_status_effects": [
        { "type": "conductive" },
        { "type": "projectile" },
        { "type": "cannotBeRotated" },
        { "type": "unique" }
    ],
    "combat_effects": [
        { "trigger": "onUse", "type": "Charm", "value": "7", "target": "allEnemies" },
        { "trigger": "onUse", "type": "ManaToSelfOnly", "value": "1" }
    ],

    "manastone": { "mana": 0, "max_mana": 7 }
}
